[


{
    "orgPost": ["テスト"]
    ,"replyPostChar": [
                    "テスト…"
                    ,"テストか…やってみよう…"
                    ,"…断る…"
                    ,"試してみるか？"
                    ]
    ,"probability":0
}



    ,{
        "orgPost": ["依頼"
                    ,"頼む"
                    ]
        ,"replyPostChar": [
                        "断る…"
                        ,"わかった…やってみよう…"
                        ,"俺のスイス銀行の口座に入金を確認次第、仕事にかかろう…"
                        ,"例のモノは…？"
                        ,"あいにくだが…　こういう形で出せる俺の答は…\nNo以外にない…"
                        ,"メールでは困る"
                        ,"OK、と答えているんだ…"
                        ,"課題を遂行するには命令系統は単純なほうがいい…おれが引き受けるとすれば"
                        ,"俺に仕事を”依頼”するのに大義名分はいらない……依頼する”本当の”理由を聞かせてくれればいい"
                        ,"俺は…引き受けると、言ったんだ…なら、話はそれで終わりだ…"
                        ,"俺は……それがどんな権力だろうと、特定の相手を顧客に持つ気はない…"
                        ,"おれのルールにあった話しならばな…"
                        ]
        ,"probability":30
    }

    ,{
        "orgPost": ["背後"
                    ,"後ろ"
                    ]
        ,"replyPostChar": [
                        "俺の後ろに立つな！！"
                        ,"…何のマネだ？これは…？"
                        ,"おれのうしろに音もたてずに立つようなまねをするな………おれはうしろに立たれるだけでもいやなのでね……"
                        ,"…うしろの守りを固めるのは、プロとしての鉄則だ…\nそれと、敵と遭遇したら迷わず引き金を引く、これも…な"
                        ,"俺は……本能的に後ろに立つ者を排除する……"
                        ]
        ,"probability":20
    }

    ,{
        "orgPost": ["自己紹介"]
        ,"replyPostChar": [
                        "…俺の名はデューク東郷…　スナイパーだ…"
                        ,"お前に語ることなどない…"
                        ,"…\n　…"
                        ,"俺は……“一人の軍隊”だ"
                        ]
        ,"probability":20
    }

    ,{
        "orgPost": ["握手"]
        ,"replyPostChar": [
                        "”利き腕”を人にあずけるほど、俺は”自信家”じゃない……\nだから、握手という習慣も……俺にはない"
                        ,"プロ…か"                        
                        ]
        ,"probability":20
    }

    ,{
        "orgPost": ["スイス"]
        ,"replyPostChar": [
                        "俺の口座はスイス銀行にある…そこへ入金してくれ…"
                        ,"スイス銀行資本を動かせるとなるとその実力は…\nおそらく世界におよんでいるはずだ…\n報復にしろ、死にしろ…おれの行く道はひとつしかない…"
                        ]
        ,"probability":30
    }

    ,{
        "orgPost": ["必ず"]
        ,"replyPostChar": [
                        "俺を誰だと思っている…仕事は確実にこなす…"
                        ,"情報は？"
                        ,"その方が…長生き出来るだろうな…"
                        ]
        ,"probability":20
    }

    ,{
        "orgPost": ["条件"]
        ,"replyPostChar": [
                        "10%の才能と20%の努力…そして、30%の臆病さ…残る40%は…運だろう…な…"
                        ,"余計な修飾語はやめて、状況を説明しろ…"
                        ,"俺は、ただ……依頼者が絶対的に求める、技量と、価値観を身につけるよう心がけているだけだ……"
                        ,"ウォッカ１オンスをトマト・ジュースで割ってくれ…"
                        ]
        ,"probability":20
    }

    ,{
        "orgPost": ["正義"]
        ,"replyPostChar": [
                        "その”正義”とやらはお前たちだけの正義じゃないのか？"
                        ,"”正義”というものはその立場で変わるものだ…"
                        ,"俺は、あんたたちに肩入れする気はない…"
                        ]
        ,"probability":20
    }

    ,{
        "orgPost": ["未熟"]
        ,"replyPostChar": [
                        "俺たちの世界では、未熟な者に”いつか”は決して訪れない…"
                        ,"…なるほど 状況は、理解した…"
                        ,"…誤解しているようだ、な…"
                        ]
        ,"probability":40
    }

    ,{
        "orgPost": ["信用"]
        ,"replyPostChar": [
                        "俺は……この目で見た事しか、信用した事がない…"
                        ,"ふふふ……女は信用しないことだ……"
                        ,"…俺に握手は無用だ…"
                        ,"罠というのは、相手に不信感を抱かせないで嵌めるもの、だ…"
                        ]
        ,"probability":30
    }

    ,{
        "orgPost": ["用件"]
        ,"replyPostChar": [
                        "… 用件を聞こうか…"
                        ,"続きを聞こう…"
                        ,"長話は無用だ…YesかNoで答えろ"
                        ,"そろそろ”本題”に入ってもらおうか…"
                        ]
        ,"probability":30
    }    

    ,{
        "orgPost": ["わからない"
                    ,"わからん"]
        ,"replyPostChar": [
                        "ググれ"
                        ,"諦めたらどうだ…？"
                        ,"すべて忘れろ"
                        ,"出来る出来ないではない、やるかやらないかだ…"
                        ,"この場を逆転できる手段があったのなら、余計な口を利いてないで行動することだ…"
                        ,"だが、思いつきも必要だ…"
                        ]
        ,"probability":10
    }   

    ,{
        "orgPost": ["真実"]
        ,"replyPostChar": [
                        "それは…　知らないほうがいい…"
                        ,"… そう考える根拠は？"
                        ,"おれは…真贋論議になんの関心もない…用件に入ってくれ…"
                        ,"おれには想像も、推察も仮定もない…あるのは事実だけだ…"
                        ]
        ,"probability":20
    }   

    ,{
        "orgPost": ["夕食"]
        ,"replyPostChar": [
                        "ボルシチを食べるのは、夜にきめている"
                        ,"俺には… そういう習慣はない…"
                        ,"いや… けっこう！"
                        ,"うまかったよ… ごちそうさん…"
                        ,"けっこうだ…"
                        ]
        ,"probability":20
    }

    ,{
        "orgPost": ["スコープ"]
        ,"replyPostChar": [
                        "予定された軌道から\n予定された場所を\n予定された速度で狙撃するのだ…\nスコープは必要ない…"
                        ]
        ,"probability":30
    }    

    ,{
        "orgPost": ["話せ"]
        ,"replyPostChar": [
                        "…何のマネだ？これは…？"
                        ,"…お前に話すことなどない…"
                        ,"お前ができることは…、黙っているということだ…"
                        ,"…ムダ口はいいから、用件を続けてくれ…"
                        ,"“話”に“裏”はないだろうな…？"
                        ,"臆病者ほど、お喋りだと、いう事だ…"
                        ,"うっ！　大蟻食い！？"
                        ]
        ,"probability":20
    }    

    ,{
        "orgPost": ["撃つ"
                    ,"撃て"
                    ]
        ,"replyPostChar": [
                        "…なぜそこまで必死になる…？"
                        ,"…お前に言われて行う仕事ではない…"
                        ,"お前に仕事の何がわかる…？"
                        ,"…俺は、依頼された標的を狙撃する事に全力をつくすだけだが…依頼者がキャンセルするなら、この仕事はやめよう…"
                        ,"相手が何者であろうと、武器を持った人間を前にして話せるほど、おれは自信家じゃあない……\nショットガンのタマをぬいてもらおう…"
                        ,"つまらんおしゃべりをしているひまに引き金をひくことだ……"
                        ]
        ,"probability":20
    }

    ,{
        "orgPost": ["おは"
                    ,"おはよう"]
        ,"replyPostChar": [
                        "…"
                        ,"挨拶は無用だ…要件を言ってくれ…"
                        ,"…あいさつは親しみ合った人たちの間でかわすものだ…"
                        ]
        ,"probability":0
    }

    ,{
        "orgPost": ["おやすみ"
                    ,"おやすみなさい"]
        ,"replyPostChar": [
                        "…"
                        ,"挨拶は無用だ…早く眠れ…"
                        ,"もういい…早く眠れ…"
                        ]
        ,"probability":0
    }

    ,{
        "orgPost": ["思う"]
        ,"replyPostChar": [
                        "…"
                        ,"…法律事務所にでも相談したらどうだ…？"
                        ,"…それは俺への依頼の範疇外だが…？"
                        ,"…気にするな…"
                        ,"すべて忘れろ"
                        ,"俺には…むかしばなしをする趣味はない…"
                        ,"…言葉や容姿だけで俺を同胞と、判断するのは勝手だが、\nそれは、日本人が持つ一番危険な、センスだな…"
                        ,"”感情”と”規律”は本質的に違うものだ…"
                        ]
        ,"probability":0
    }

    ,{
        "orgPost": ["ネット"]
        ,"replyPostChar": [
                        "ネットの中では、大人も子供も、男も女もないんじゃないか？"
                        ,"俺は犠牲になる気はない…自分が生き抜くために、やるのだ…"
                        ]
        ,"probability":5
    }

    ,{
        "orgPost": ["退勤"]
        ,"replyPostChar": [
                        "…ならさっさと帰ったらどうだ…？"
                        ,"…報告の義務はない…"
                        ,"…もういい…帰れ…"
                        ,"…もう必要ない…ご苦労だった…"
                        ,"いや…おまえは間違ってはいなかった…証人は消せ…鉄則だ…"
                        ,"…そっちが入ってくる15分前からここにいる…"
                        ]
        ,"probability":20
    }
    
    ,{
        "orgPost": ["ありがとう"
                    ,"礼"]
        ,"replyPostChar": [
                        "…"
                        ,"…礼には及ばない…俺は俺の仕事をしたまでだ…"
                        ,"…礼には及ばない…"
                        ]
        ,"probability":20
    }

    ,{
        "orgPost": ["回数"
                    ,"回目"]
        ,"replyPostChar": [
                        "一つでいい、必要なのは 一回だけだ…"
                        ,"二度はない…一度のその瞬間だけだ…"
                        ]
        ,"probability":20
    } 

    ,{
        "orgPost": ["プロ"]
        ,"replyPostChar": [
                        "最後までチャンスを待つのが本当のプロだ…"
                        ,"プロは決して自分の手を相手にあずけるようなことはしない…"
                        ,"おまえ……プロの掟を知っているな？ プロは二重に仕事をひきうけないことだ……"
                        ,"俺は、仕事に入る前……それが情報不足だと思った時にはその道のプロを雇う……\nそして雇う時には相手を選ぶ……選んだ相手が、俺を裏切らない限り、相手の調査を信じて行動するしかないと思っている……"
                        ]
        ,"probability":20
    }    

]